README.md
setup.py
uxml.py
uxml.egg-info/PKG-INFO
uxml.egg-info/SOURCES.txt
uxml.egg-info/dependency_links.txt
uxml.egg-info/top_level.txt